aivid/__init__.py
aivid/_version.py
aivid/analyze.py
aivid/cli.py
aivid/config.py
aivid/py.typed
aivid/detectors/__init__.py
aivid/detectors/audioseal.py
aivid/detectors/base.py
aivid/detectors/videoseal.py
aivid/downloaders/__init__.py
aivid/downloaders/base.py
aivid/downloaders/sora.py
aivid/downloaders/tiktok.py
aivid/downloaders/youtube.py
aivid/extractors/__init__.py
aivid/extractors/base.py
aivid/extractors/c2pa.py
aivid/extractors/c2patool.py
aivid/extractors/exiftool.py
aivid/extractors/ffprobe.py
aivid/extractors/heuristic.py
aivid/extractors/tiktok_api.py
aivid/extractors/youtube_api.py
aivid/formatters/__init__.py
aivid/formatters/c2pa.py
aivid/formatters/default.py
aivid/formatters/full.py
aivid/formatters/json.py
aivid/formatters/quiet.py
aivid/models/__init__.py
aivid/models/ai.py
aivid/models/descriptive.py
aivid/models/file.py
aivid/models/provenance.py
aivid/models/raw.py
aivid/models/source.py
aivid/models/technical.py
aivid/models/video.py
aivid/models/watermark.py
aivid/utils/__init__.py
aivid/utils/container.py
aivid/utils/deps.py
aivid/utils/url_parser.py
aivid-0.3.0.dist-info/METADATA
aivid-0.3.0.dist-info/WHEEL
aivid-0.3.0.dist-info/entry_points.txt
aivid-0.3.0.dist-info/licenses/LICENSE
aivid-0.3.0.dist-info/RECORD
