Metadata-Version: 2.4
Name: aivid
Version: 0.3.0
Summary: AI video toolkit - detect, analyze, and work with AI-generated videos
Project-URL: Homepage, https://github.com/socialnetwork0/aivid
Project-URL: Documentation, https://github.com/socialnetwork0/aivid#readme
Project-URL: Repository, https://github.com/socialnetwork0/aivid
Project-URL: Issues, https://github.com/socialnetwork0/aivid/issues
Project-URL: Changelog, https://github.com/socialnetwork0/aivid/blob/main/CHANGELOG.md
Author: SocialNetwork0
License-Expression: MIT
License-File: LICENSE
Keywords: ai,ai-generated,c2pa,dalle,deepfake,detection,firefly,gemini,kling,luma,metadata,midjourney,pika,runway,sora,synthetic-media,veo,video
Classifier: Development Status :: 4 - Beta
Classifier: Environment :: Console
Classifier: Intended Audience :: Developers
Classifier: Intended Audience :: Science/Research
Classifier: License :: OSI Approved :: MIT License
Classifier: Operating System :: OS Independent
Classifier: Programming Language :: Python :: 3
Classifier: Programming Language :: Python :: 3.10
Classifier: Programming Language :: Python :: 3.11
Classifier: Programming Language :: Python :: 3.12
Classifier: Programming Language :: Python :: 3.13
Classifier: Topic :: Multimedia :: Video
Classifier: Topic :: Scientific/Engineering :: Artificial Intelligence
Classifier: Typing :: Typed
Requires-Python: >=3.10
Requires-Dist: pydantic>=2.0
Provides-Extra: all
Requires-Dist: audioseal>=0.1.0; extra == 'all'
Requires-Dist: c2pa-python>=0.6.0; extra == 'all'
Requires-Dist: httpx>=0.25.0; extra == 'all'
Requires-Dist: pyexiftool>=0.5.0; extra == 'all'
Requires-Dist: pymediainfo>=6.0; extra == 'all'
Requires-Dist: pyyaml>=6.0; extra == 'all'
Requires-Dist: torch>=2.0; extra == 'all'
Requires-Dist: torchaudio>=2.0; extra == 'all'
Requires-Dist: yt-dlp>=2024.1.0; extra == 'all'
Provides-Extra: api
Requires-Dist: httpx>=0.25.0; extra == 'api'
Provides-Extra: c2pa
Requires-Dist: c2pa-python>=0.6.0; extra == 'c2pa'
Provides-Extra: config
Requires-Dist: pyyaml>=6.0; extra == 'config'
Provides-Extra: default
Requires-Dist: c2pa-python>=0.6.0; extra == 'default'
Provides-Extra: dev
Requires-Dist: mypy>=1.0; extra == 'dev'
Requires-Dist: pre-commit>=3.0; extra == 'dev'
Requires-Dist: pytest-cov>=4.0; extra == 'dev'
Requires-Dist: pytest>=8.0; extra == 'dev'
Requires-Dist: ruff>=0.8; extra == 'dev'
Provides-Extra: docs
Requires-Dist: mkdocs-material>=9.0; extra == 'docs'
Requires-Dist: mkdocs>=1.5; extra == 'docs'
Requires-Dist: mkdocstrings[python]>=0.24; extra == 'docs'
Provides-Extra: download
Requires-Dist: yt-dlp>=2024.1.0; extra == 'download'
Provides-Extra: exif
Requires-Dist: pyexiftool>=0.5.0; extra == 'exif'
Provides-Extra: full
Requires-Dist: c2pa-python>=0.6.0; extra == 'full'
Requires-Dist: httpx>=0.25.0; extra == 'full'
Requires-Dist: pyexiftool>=0.5.0; extra == 'full'
Requires-Dist: pymediainfo>=6.0; extra == 'full'
Requires-Dist: pyyaml>=6.0; extra == 'full'
Requires-Dist: yt-dlp>=2024.1.0; extra == 'full'
Provides-Extra: lite
Requires-Dist: c2pa-python>=0.6.0; extra == 'lite'
Requires-Dist: httpx>=0.25.0; extra == 'lite'
Requires-Dist: pyexiftool>=0.5.0; extra == 'lite'
Requires-Dist: pyyaml>=6.0; extra == 'lite'
Requires-Dist: yt-dlp>=2024.1.0; extra == 'lite'
Provides-Extra: mediainfo
Requires-Dist: pymediainfo>=6.0; extra == 'mediainfo'
Provides-Extra: watermark
Requires-Dist: audioseal>=0.1.0; extra == 'watermark'
Requires-Dist: torch>=2.0; extra == 'watermark'
Requires-Dist: torchaudio>=2.0; extra == 'watermark'
